json_prettifier/__init__.py
json_prettifier/cli.py
json_prettifier-0.1.0.dist-info/METADATA
json_prettifier-0.1.0.dist-info/WHEEL
json_prettifier-0.1.0.dist-info/entry_points.txt
json_prettifier-0.1.0.dist-info/top_level.txt
json_prettifier-0.1.0.dist-info/RECORD
